Metadata-Version: 2.1
Name: skibiditoilet232
Version: 0.0
Summary: skibiditoilet232
Author-email: applepro285@gmail.com
